caqtus_devices/cameras/hamamatsu_orca_quest/__about__.py
caqtus_devices/cameras/hamamatsu_orca_quest/__init__.py
caqtus_devices/cameras/hamamatsu_orca_quest/_compiler.py
caqtus_devices/cameras/hamamatsu_orca_quest/_extension.py
caqtus_devices/cameras/hamamatsu_orca_quest/py.typed
caqtus_devices/cameras/hamamatsu_orca_quest/configuration/__init__.py
caqtus_devices/cameras/hamamatsu_orca_quest/configuration/configuration.py
caqtus_devices/cameras/hamamatsu_orca_quest/configuration_editor/__init__.py
caqtus_devices/cameras/hamamatsu_orca_quest/configuration_editor/orca_quest_config_editor.py
caqtus_devices/cameras/hamamatsu_orca_quest/runtime/__init__.py
caqtus_devices/cameras/hamamatsu_orca_quest/runtime/_logger.py
caqtus_devices/cameras/hamamatsu_orca_quest/runtime/_runtime.py
caqtus_devices/cameras/hamamatsu_orca_quest/runtime/dcam.py
caqtus_devices/cameras/hamamatsu_orca_quest/runtime/dcamapi4.py
caqtus_devices_hamamatsu_orca_quest-2.6.0.dist-info/METADATA
caqtus_devices_hamamatsu_orca_quest-2.6.0.dist-info/WHEEL
caqtus_devices_hamamatsu_orca_quest-2.6.0.dist-info/licenses/license.md
caqtus_devices_hamamatsu_orca_quest-2.6.0.dist-info/RECORD
